ts4uc/__init__.py
ts4uc/helpers.py
ts4uc/agents/__init__.py
ts4uc/agents/solve_model_free.py
ts4uc/agents/a3c/__init__.py
ts4uc/agents/a3c/a3c.py
ts4uc/agents/a3c/train.py
ts4uc/agents/ppo/__init__.py
ts4uc/agents/ppo/ppo.py
ts4uc/agents/ppo/train.py
ts4uc/agents/ppo_async/__init__.py
ts4uc/agents/ppo_async/ac_agent.py
ts4uc/agents/ppo_async/train.py
ts4uc/agents/sac/__init__.py
ts4uc/agents/sac/sac.py
ts4uc/agents/sac/train.py
ts4uc/tree_search/__init__.py
ts4uc/tree_search/algos.py
ts4uc/tree_search/anytime.py
ts4uc/tree_search/day_ahead.py
ts4uc/tree_search/expansion.py
ts4uc/tree_search/informed_search.py
ts4uc/tree_search/node.py
ts4uc/tree_search/rolling_horizon.py
ts4uc/tree_search/scenarios.py
ts4uc/tree_search/tree_search.py
ts4uc/tree_search/mcts/__init__.py
ts4uc/tree_search/mcts/node.py
ts4uc/tree_search/mcts/priority_list.py
ts4uc-0.0.1.dist-info/LICENSE
ts4uc-0.0.1.dist-info/METADATA
ts4uc-0.0.1.dist-info/WHEEL
ts4uc-0.0.1.dist-info/top_level.txt
ts4uc-0.0.1.dist-info/RECORD
