Metadata-Version: 2.1
Name: ts4uc
Version: 0.0.1
Summary: Tree search and reinforcement learning for the unit commitment problem
Author: Patrick de Mars
Author-email: pwdemars@gmail.com
Classifier: Programming Language :: Python :: 3
Classifier: License :: OSI Approved :: MIT License
Classifier: Operating System :: OS Independent
Requires-Python: >=3.9
License-File: LICENSE
Requires-Dist: numpy
Requires-Dist: pandas
Requires-Dist: torch (==1.8.0)
Requires-Dist: pytest
Requires-Dist: rl4uc
Requires-Dist: scipy
